ETemplator-0.2.dist-info/DESCRIPTION.rst
ETemplator-0.2.dist-info/METADATA
ETemplator-0.2.dist-info/RECORD
ETemplator-0.2.dist-info/WHEEL
ETemplator-0.2.dist-info/metadata.json
ETemplator-0.2.dist-info/top_level.txt
templator/__init__.py
