Metadata-Version: 2.0
Name: ETemplator
Version: 0.2
Summary: App for creating and populating email templates
Home-page: http://amitbhat.in
Author: amit
Author-email: amit.bhat@outlook.com
License: MIT
Platform: UNKNOWN
